{"items":[{"id":2987698,"name":"RazorSecure","hq_locations":[],"industries":[],"path":"razorsecure_1"},{"id":1448158,"name":"RazorSecure","hq_locations":[{"id":2261897,"address":"Belvedere House, Basing View, Basingstoke RG21 4HG","street":"Basing View","street_number":"","zip":"RG21 4HG","lat":51.2686728,"lon":-1.0725726,"country":{"id":9,"name":"United Kingdom","lat":51.465986,"lon":-1.281401,"trade_register_office":"Companies House"},"city":{"id":99,"name":"Basingstoke","lat":51.26654,"lon":-1.092396},"continent":{"id":3,"name":"Europe"},"is_headquarters":true,"is_founding_location":false,"trade_register_number":"09370482"}],"industries":[{"id":1262,"name":"security"}],"path":"razorsecure"}],"total":2}